cbits/__init__.py
cbits/_cbits.so
cbits-0.2.0.dist-info/METADATA
cbits-0.2.0.dist-info/WHEEL
cbits-0.2.0.dist-info/RECORD
cbits-0.2.0.dist-info/licenses/LICENSE
