Metadata-Version: 2.4
Name: cbits
Version: 0.2.0
Summary: High-performance BitVector with C backend.
Keywords: bitvector,c-extension,python,bits
Author: lambdaphoenix
License-Expression: Apache-2.0
License-File: LICENSE
Classifier: Programming Language :: Python :: 3.8
Classifier: Programming Language :: Python :: 3.9
Classifier: Programming Language :: Python :: 3.10
Classifier: Programming Language :: Python :: 3.11
Classifier: Programming Language :: Python :: 3.12
Classifier: Programming Language :: Python :: 3.13
Classifier: Programming Language :: C
Classifier: Operating System :: OS Independent
Classifier: Topic :: Software Development :: Libraries
Project-URL: Homepage, https://github.com/lambdaphoenix/cbits
Project-URL: Source, https://github.com/lambdaphoenix/cbits.git
Project-URL: Issue Tracker, https://github.com/lambdaphoenix/cbits/issues
Project-URL: Documentation, https://lambdaphoenix.github.io/cbits/
Requires-Python: >=3.8
